conversation_tk-2.6.0.dist-info/licenses/LICENSE
ctk/__init__.py
ctk/api.py
ctk/cli.py
ctk/cli_config.py
ctk/cli_conv.py
ctk/cli_db.py
ctk/cli_lib.py
ctk/cli_llm.py
ctk/cli_net.py
ctk/mcp_server.py
ctk/core/__init__.py
ctk/core/command_dispatcher.py
ctk/core/command_options.py
ctk/core/config.py
ctk/core/conversation_display.py
ctk/core/conversation_index.py
ctk/core/database.py
ctk/core/db_helpers.py
ctk/core/db_models.py
ctk/core/db_operations.py
ctk/core/formatting.py
ctk/core/models.py
ctk/core/network_analysis.py
ctk/core/plugin.py
ctk/core/prompts.py
ctk/core/sanitizer.py
ctk/core/shell_completer.py
ctk/core/shell_parser.py
ctk/core/similarity.py
ctk/core/slug.py
ctk/core/tools.py
ctk/core/tools_registry.py
ctk/core/tree.py
ctk/core/vfs.py
ctk/core/vfs_navigator.py
ctk/core/views.py
ctk/core/commands/__init__.py
ctk/core/commands/chat.py
ctk/core/commands/database.py
ctk/core/commands/llm.py
ctk/core/commands/navigation.py
ctk/core/commands/organization.py
ctk/core/commands/search.py
ctk/core/commands/session.py
ctk/core/commands/settings.py
ctk/core/commands/tree_nav.py
ctk/core/commands/unix.py
ctk/core/commands/visualization.py
ctk/integrations/__init__.py
ctk/integrations/chat/__init__.py
ctk/integrations/chat/tui.py
ctk/integrations/embeddings/__init__.py
ctk/integrations/embeddings/base.py
ctk/integrations/embeddings/ollama.py
ctk/integrations/embeddings/tfidf.py
ctk/integrations/exporters/__init__.py
ctk/integrations/exporters/echo.py
ctk/integrations/exporters/html.py
ctk/integrations/exporters/hugo.py
ctk/integrations/exporters/json.py
ctk/integrations/exporters/jsonl.py
ctk/integrations/exporters/markdown.py
ctk/integrations/importers/__init__.py
ctk/integrations/importers/anthropic.py
ctk/integrations/importers/copilot.py
ctk/integrations/importers/filesystem_coding.py
ctk/integrations/importers/gemini.py
ctk/integrations/importers/jsonl.py
ctk/integrations/importers/openai.py
ctk/integrations/llm/__init__.py
ctk/integrations/llm/anthropic.py
ctk/integrations/llm/base.py
conversation_tk-2.6.0.dist-info/METADATA
conversation_tk-2.6.0.dist-info/WHEEL
conversation_tk-2.6.0.dist-info/entry_points.txt
conversation_tk-2.6.0.dist-info/top_level.txt
conversation_tk-2.6.0.dist-info/RECORD
