Metadata-Version: 2.4
Name: conversation-tk
Version: 2.6.0
Summary: A robust toolkit for managing tree-based conversations from multiple sources
Home-page: https://github.com/queelius/ctk
Author: Alex Towell
Author-email: lex@metafunctor.com
Classifier: Development Status :: 4 - Beta
Classifier: Intended Audience :: Developers
Classifier: Topic :: Software Development :: Libraries :: Python Modules
Classifier: License :: OSI Approved :: MIT License
Classifier: Programming Language :: Python :: 3
Classifier: Programming Language :: Python :: 3.8
Classifier: Programming Language :: Python :: 3.9
Classifier: Programming Language :: Python :: 3.10
Classifier: Programming Language :: Python :: 3.11
Requires-Python: >=3.8
License-File: LICENSE
Requires-Dist: sqlalchemy>=2.0.0
Requires-Dist: alembic>=1.13.0
Requires-Dist: pydantic>=2.0.0
Requires-Dist: requests>=2.31.0
Requires-Dist: rich>=13.0.0
Requires-Dist: mcp>=1.0.0
Requires-Dist: networkx>=3.0
Requires-Dist: scikit-learn>=1.3.0
Requires-Dist: numpy>=1.24.0
Provides-Extra: dev
Requires-Dist: pytest>=7.0; extra == "dev"
Requires-Dist: pytest-cov>=4.0; extra == "dev"
Requires-Dist: black>=23.0; extra == "dev"
Requires-Dist: flake8>=6.0; extra == "dev"
Requires-Dist: mypy>=1.0; extra == "dev"
Dynamic: author
Dynamic: author-email
Dynamic: classifier
Dynamic: description
Dynamic: description-content-type
Dynamic: home-page
Dynamic: license-file
Dynamic: provides-extra
Dynamic: requires-dist
Dynamic: requires-python
Dynamic: summary
